spiders/realtime/__init__.py
spiders/realtime/link_filter.py
spiders/realtime/normalize.py
spiders/realtime/rt_logger.py
link_quality-2.0.2.dist-info/METADATA
link_quality-2.0.2.dist-info/WHEEL
link_quality-2.0.2.dist-info/top_level.txt
link_quality-2.0.2.dist-info/RECORD
