Metadata-Version: 2.4
Name: link-quality
Version: 2.0.2
Summary: link-quality
Author: daoya
License: MIT
Classifier: Programming Language :: Python :: 3
Requires-Python: >=3.6
Requires-Dist: tldextract
Requires-Dist: urllib3
Requires-Dist: aioredis
Requires-Dist: aiocache
Requires-Dist: loguru
Requires-Dist: multipledispatch
Requires-Dist: tenacity
Dynamic: author
Dynamic: classifier
Dynamic: license
Dynamic: requires-dist
Dynamic: requires-python
Dynamic: summary
